ezekiel.py
ezekiel-0.0.1.dist-info/METADATA
ezekiel-0.0.1.dist-info/WHEEL
ezekiel-0.0.1.dist-info/top_level.txt
ezekiel-0.0.1.dist-info/RECORD
