Metadata-Version: 2.4
Name: ezekiel
Version: 0.0.1
Summary: Placeholder package to reserve the Ezekiel project name
Author-email: Processus Thief <processus@thiefin.fr>
License-Expression: GPL-3.0-only
Classifier: Development Status :: 1 - Planning
Classifier: Intended Audience :: Developers
Classifier: Topic :: Security
Classifier: Programming Language :: Python :: 3
Requires-Python: >=3.8
